CHANGES
LICENSE
MANIFEST.in
NOTICE
README.md
setup.py
DAFI.egg-info/PKG-INFO
DAFI.egg-info/SOURCES.txt
DAFI.egg-info/dependency_links.txt
DAFI.egg-info/requires.txt
DAFI.egg-info/top_level.txt
bin/dafi
dafi/__init__.py
dafi/inverse.py
dafi/main.py
dafi/physics_model.py
dafi/random_field/__init__.py
dafi/random_field/covariance.py
dafi/random_field/field.py
dafi/random_field/foam_utilities.py
dafi/tests/__init__.py
dafi/tests/test_dafi.py