Metadata-Version: 2.1
Name: DAFI
Version: 1.0.1
Summary: Ensemble based data-assimilation and field inversion.
Home-page: https://github.com/xiaoh/DAFI
Author: Virginia Tech
License: Apache 2.0
Download-URL: https://github.com/xiaoh/DAFI/archive/refs/tags/1.0.0.tar.gz
Keywords: Data Assimilation,Field Inversion
Platform: UNKNOWN
Classifier: Development Status :: 4 - Beta
Classifier: Intended Audience :: Science/Research
Classifier: Topic :: Scientific/Engineering
Classifier: License :: OSI Approved :: Apache Software License
Classifier: Programming Language :: Python :: 3.8
